easysetup/appinfo.py
easysetup/AUTHORS.txt
easysetup/ChangeLog.txt
easysetup/common.py
easysetup/easysetup.py
easysetup/LICENSE.txt
easysetup/localization.py
easysetup/README.txt
easysetup/usage.txt
easysetup/usage_pt.txt
easysetup/__init__.py
easysetup/doc/.buildinfo
easysetup/doc/authors.html
easysetup/doc/changelog.html
easysetup/doc/easysetup.pdf
easysetup/doc/genindex.html
easysetup/doc/index.html
easysetup/doc/license.html
easysetup/doc/objects.inv
easysetup/doc/py-modindex.html
easysetup/doc/readme.html
easysetup/doc/reference.html
easysetup/doc/search.html
easysetup/doc/searchindex.js
easysetup/doc/_modules/common.html
easysetup/doc/_modules/easysetup.html
easysetup/doc/_modules/index.html
easysetup/doc/_modules/localization.html
easysetup/doc/_sources/authors.txt
easysetup/doc/_sources/changelog.txt
easysetup/doc/_sources/index.txt
easysetup/doc/_sources/license.txt
easysetup/doc/_sources/readme.txt
easysetup/doc/_sources/reference.txt
easysetup/doc/_static/ajax-loader.gif
easysetup/doc/_static/alabaster.css
easysetup/doc/_static/basic.css
easysetup/doc/_static/comment-bright.png
easysetup/doc/_static/comment-close.png
easysetup/doc/_static/comment.png
easysetup/doc/_static/doctools.js
easysetup/doc/_static/down-pressed.png
easysetup/doc/_static/down.png
easysetup/doc/_static/file.png
easysetup/doc/_static/jquery-1.11.1.js
easysetup/doc/_static/jquery.js
easysetup/doc/_static/minus.png
easysetup/doc/_static/plus.png
easysetup/doc/_static/pygments.css
easysetup/doc/_static/searchtools.js
easysetup/doc/_static/underscore-1.3.1.js
easysetup/doc/_static/underscore.js
easysetup/doc/_static/up-pressed.png
easysetup/doc/_static/up.png
easysetup/doc/_static/websupport.js
easysetup/template/.gitignore
easysetup/template/.travis.yml
easysetup/template/appinfo.py
easysetup/template/appveyor.yml
easysetup/template/AUTHORS.rst
easysetup/template/build.cmd
easysetup/template/ChangeLog.rst
easysetup-0.0.19.dist-info/DESCRIPTION.rst
easysetup-0.0.19.dist-info/entry_points.txt
easysetup-0.0.19.dist-info/METADATA
easysetup-0.0.19.dist-info/metadata.json
easysetup-0.0.19.dist-info/RECORD
easysetup-0.0.19.dist-info/top_level.txt
easysetup-0.0.19.dist-info/WHEEL
