Metadata-Version: 1.1
Name: easysetup
Version: 0.0.19
Summary: Helps creating a package distribution setup, that also runs tests, checkers and creates HTML and PDF documentation, for Windows users.
Home-page: https://github.com/jcrmatos/easysetup
Author: Joao Carlos Roseta Matos
Author-email: jcrmatos@gmail.com
License: GNU General Public License v2 or later (GPLv2+)
Keywords: e,a,s,y, ,s,e,t,u,p, ,s,e,t,u,p,t,o,o,l,s
Platform: UNKNOWN
Classifier: Development Status :: 4 - Beta
Classifier: Environment :: Console
Classifier: Intended Audience :: Developers
Classifier: License :: OSI Approved :: GNU General Public License v2 or later (GPLv2+)
Classifier: Natural Language :: English
Classifier: Operating System :: Microsoft :: Windows
Classifier: Programming Language :: Python
Classifier: Programming Language :: Python :: 2
Classifier: Programming Language :: Python :: 2.7
Classifier: Programming Language :: Python :: 3
Classifier: Programming Language :: Python :: 3.4
Classifier: Topic :: Software Development :: Build Tools
